{"admission_count": {"order": [0, 1, 2], "seasonal_order": [1, 0, 2, 52], "IS_MEA": 50.77}, "discharge_count": {"order": [0, 1, 2], "seasonal_order": [2, 0, 0, 52], "IS_MEA": 50.15}, "Avg LOS Days": {"order": [1, 1, 1], "seasonal_order": [0, 0, 0, 52], "IS_MEA": 9.72}, "total_felony_crimes": {"order": [0, 1, 1], "seasonal_order": [1, 0, 0, 52], "IS_MEA": 128.56}, "murder_homicide_count": {"order": [3, 0, 3], "seasonal_order": [0, 0, 1, 52], "IS_MEA": 2.45}, "robbery_count": {"order": [4, 0, 0], "seasonal_order": [1, 0, 0, 52], "IS_MEA": 20.6}, "assault_count": {"order": [3, 0, 3], "seasonal_order": [1, 0, 0, 52], "IS_MEA": 29.4}, "burglary_count": {"order": [0, 1, 1], "seasonal_order": [0, 0, 0, 52], "IS_MEA": 20.57}, "rape_count": {"order": [5, 0, 0], "seasonal_order": [0, 0, 2, 52], "IS_MEA": 5.43}, "grand_larceny_count": {"order": [1, 1, 0], "seasonal_order": [2, 0, 0, 52], "IS_MEA": 50.64}, "grand_larceny_vehicle_count": {"order": [3, 1, 0], "seasonal_order": [2, 0, 0, 52], "IS_MEA": 15.6}, "weapons_count": {"order": [3, 0, 0], "seasonal_order": [0, 0, 2, 52], "IS_MEA": 11.92}, "total_felony_arrest": {"order": [2, 1, 4], "seasonal_order": [2, 0, 0, 52], "IS_MEA": 119.63}, "arrest_murder_homicide_count": {"order": [5, 0, 0], "seasonal_order": [1, 0, 0, 52], "IS_MEA": 6.32}, "arrest_robbery_count": {"order": [1, 1, 1], "seasonal_order": [1, 0, 1, 52], "IS_MEA": 20.4}, "arrest_assault_count": {"order": [0, 1, 3], "seasonal_order": [1, 0, 1, 52], "IS_MEA": 25.08}, "arrest_burglary_count": {"order": [2, 0, 2], "seasonal_order": [0, 0, 0, 52], "IS_MEA": 19.39}, "arrest_rape_count": {"order": [5, 0, 0], "seasonal_order": [0, 0, 0, 52], "IS_MEA": 3.28}, "arrest_grand_larceny_count": {"order": [0, 1, 2], "seasonal_order": [2, 0, 0, 52], "IS_MEA": 26.9}, "arrest_grand_larceny_vehicle_count": {"order": [5, 0, 0], "seasonal_order": [1, 0, 0, 52], "IS_MEA": 6.71}, "arrest_weapons_count": {"order": [3, 0, 0], "seasonal_order": [0, 0, 2, 52], "IS_MEA": 16.2}}